misophonia_data_analysis/SoundDataAnalysis.py
misophonia_data_analysis/__init__.py
misophonia_data_analysis/_version.py
misophonia_data_analysis/cli.py
misophonia_data_analysis/Mapping/__init__.py
misophonia_data_analysis/Raw Data/__init__.py
misophonia_data_analysis-1.0.0.dist-info/METADATA
misophonia_data_analysis-1.0.0.dist-info/WHEEL
misophonia_data_analysis-1.0.0.dist-info/entry_points.txt
misophonia_data_analysis-1.0.0.dist-info/top_level.txt
misophonia_data_analysis-1.0.0.dist-info/RECORD
