Metadata-Version: 2.1
Name: misophonia_data_analysis
Version: 1.0.0
Requires-Dist: pandas >=1.5.2
